LICENSE
pyproject.toml
readme.md
setup.py
db/__init__.py
db/db_manager.py
parser/__init__.py
parser/base_parser.py
parser/classes_parser.py
parser/deities_parser.py
parser/feats_parser.py
parser/items_parser.py
parser/monsters_parser.py
parser/races_parser.py
parser/spells_parser.py
parser/templates_parser.py
project_mjolnir.egg-info/PKG-INFO
project_mjolnir.egg-info/SOURCES.txt
project_mjolnir.egg-info/dependency_links.txt
project_mjolnir.egg-info/requires.txt
project_mjolnir.egg-info/top_level.txt
utils/__init__.py
utils/detector.py
utils/doc_converter.py
utils/text_cleaner.py