Metadata-Version: 2.4
Name: project-mjolnir
Version: 2.0.0
Summary: Modular D&D 3.5e Parser and Database Builder
Author: DaveTmire85
License: MIT
Classifier: Programming Language :: Python :: 3
Classifier: License :: OSI Approved :: MIT License
Classifier: Operating System :: OS Independent
Requires-Python: >=3.10
License-File: LICENSE
Requires-Dist: python-docx>=0.8.11
Dynamic: license-file
Dynamic: requires-python
